camera_enum/__init__.py
camera_enum/camera_enum.pyd
camera_enum/py.typed
windows_camera_enum-1.0.4.dist-info/METADATA
windows_camera_enum-1.0.4.dist-info/WHEEL
windows_camera_enum-1.0.4.dist-info/licenses/LICENSE
windows_camera_enum-1.0.4.dist-info/RECORD
