Metadata-Version: 2.2
Name: windows-camera-enum
Version: 1.0.4
Summary: Windows camera device enumeration using DirectShow APIs
Author-Email: Jonathan <jonathan@cheap-geeks.com>
License: MIT
Classifier: Development Status :: 5 - Production/Stable
Classifier: Environment :: Console
Classifier: Intended Audience :: Developers
Classifier: Intended Audience :: Education
Classifier: Intended Audience :: Information Technology
Classifier: Intended Audience :: Science/Research
Classifier: License :: OSI Approved :: MIT License
Classifier: Operating System :: Microsoft :: Windows
Classifier: Programming Language :: Python
Classifier: Programming Language :: Python :: 3
Classifier: Programming Language :: Python :: 3 :: Only
Classifier: Programming Language :: Python :: 3.8
Classifier: Programming Language :: Python :: 3.9
Classifier: Programming Language :: Python :: 3.10
Classifier: Programming Language :: Python :: 3.11
Classifier: Programming Language :: Python :: 3.12
Classifier: Programming Language :: Python :: 3.13
Classifier: Programming Language :: C++
Classifier: Programming Language :: Python :: Implementation :: CPython
Classifier: Topic :: Scientific/Engineering
Classifier: Topic :: Software Development
Project-URL: Homepage, https://github.com/thecheapgeek/python-lite-camera
Project-URL: Repository, https://github.com/thecheapgeek/python-lite-camera
Project-URL: Documentation, https://github.com/thecheapgeek/python-lite-camera#readme
Project-URL: Changelog, https://github.com/thecheapgeek/python-lite-camera/blob/main/CHANGELOG.md
Project-URL: Issues, https://github.com/thecheapgeek/python-lite-camera/issues
Requires-Python: >=3.8
